binance_interface/__init__.py
binance_interface/api/__init__.py
binance_interface/api/client.py
binance_interface/api/proxy_host.py
binance_interface/api/cm/__init__.py
binance_interface/api/cm/cm_account_trade.py
binance_interface/api/cm/cm_market.py
binance_interface/api/cm/cm_portfolio.py
binance_interface/api/eo/__init__.py
binance_interface/api/eo/eo_account_trade.py
binance_interface/api/eo/eo_market.py
binance_interface/api/eo/eo_market_maker.py
binance_interface/api/margin/__init__.py
binance_interface/api/margin/margin_account_trade.py
binance_interface/api/margin/margin_blvt.py
binance_interface/api/other/__init__.py
binance_interface/api/other/auto_invest.py
binance_interface/api/other/bs_wap.py
binance_interface/api/other/c2c.py
binance_interface/api/other/convert.py
binance_interface/api/other/crypto_loans.py
binance_interface/api/other/fiat.py
binance_interface/api/other/futures.py
binance_interface/api/other/futures_algo.py
binance_interface/api/other/gift_card.py
binance_interface/api/other/mining.py
binance_interface/api/other/nft.py
binance_interface/api/other/pay.py
binance_interface/api/other/portfolio.py
binance_interface/api/other/rebate.py
binance_interface/api/other/simple_earn.py
binance_interface/api/other/sub_account.py
binance_interface/api/other/vip_loans.py
binance_interface/api/other/wallet.py
binance_interface/api/pm/__init__.py
binance_interface/api/pm/pm_account.py
binance_interface/api/pm/pm_cancel_order.py
binance_interface/api/pm/pm_get_order.py
binance_interface/api/pm/pm_market.py
binance_interface/api/pm/pm_set_order.py
binance_interface/api/spot/__init__.py
binance_interface/api/spot/spot_account.py
binance_interface/api/spot/spot_algo.py
binance_interface/api/spot/spot_market.py
binance_interface/api/spot/spot_trade.py
binance_interface/api/um/__init__.py
binance_interface/api/um/um_account_trade.py
binance_interface/api/um/um_market.py
binance_interface/api/um/um_portfolio.py
binance_interface/app/__init__.py
binance_interface-2.0.5.dist-info/METADATA
binance_interface-2.0.5.dist-info/WHEEL
binance_interface-2.0.5.dist-info/top_level.txt
binance_interface-2.0.5.dist-info/RECORD
