Metadata-Version: 2.1
Name: binance-interface
Version: 2.0.5
Summary: Python Binance API Interface and Advanced APP Packaging Methods
Home-page: https://github.com/pyted/binance_interface
Author: pyted
Author-email: pyted@outlook.com
License: MIT
Classifier: License :: OSI Approved :: MIT License
Classifier: Programming Language :: Python
Classifier: Programming Language :: Python :: 3
Classifier: Programming Language :: Python :: 3.6
Classifier: Programming Language :: Python :: Implementation :: CPython
Classifier: Programming Language :: Python :: Implementation :: PyPy
Requires-Python: >=3.8.0
Requires-Dist: requests
Requires-Dist: pandas
Requires-Dist: numpy
Requires-Dist: paux (>=1.0.13)
Requires-Dist: candlelite (>=1.0.10)
